[
    {
        "name": "GOMEZ_HOUSE",
        "collectibles": {},
        "entrances": [
            {
                "volume_id": 1,
                "viewpoint": "RIGHT",
                "original_destination": "VILLAGEVILLE_3D"
            }
        ]
    },
    {
        "name": "VILLAGEVILLE_3D",
        "collectibles": {
            "bits": 4,
            "keys": 1
        },
        "entrances": [
            {
                "volume_id": 1,
                "viewpoint": "FRONT",
                "original_destination": "GEEZER_HOUSE"
            },
            {
                "volume_id": 2,
                "viewpoint": "FRONT",
                "original_destination": "SCHOOL"
            },
            {
                "volume_id": 3,
                "viewpoint": "FRONT",
                "original_destination": "KITCHEN"
            },
            {
                "volume_id": 4,
                "viewpoint": "FRONT",
                "original_destination": "GOMEZ_HOUSE"
            },
            {
                "volume_id": 6,
                "viewpoint": "FRONT",
                "original_destination": "BOILEROOM",
                "locked": true
            },
            {
                "volume_id": 10,
                "viewpoint": "FRONT",
                "original_destination": "PARLOR"
            },
            {
                "volume_id": 12,
                "viewpoint": "FRONT",
                "original_destination": "BIG_TOWER",
                "cubes_required": 1
            },
            {
                "volume_id": 13,
                "viewpoint": "RIGHT",
                "original_destination": "ABANDONED_A"
            },
            {
                "volume_id": 14,
                "viewpoint": "BACK",
                "original_destination": "ABANDONED_B"
            },
            {
                "volume_id": 15,
                "viewpoint": "LEFT",
                "original_destination": "ABANDONED_C"
            }
        ]
    },
    {
        "name": "PARLOR",
        "collectibles": {
            "anti_cubes": 1,
            "keys": 1
        },
        "entrances": [
            {
                "volume_id": 1,
                "viewpoint":"RIGHT",
                "original_destination": "VILLAGEVILLE_3D"
            }
        ]
    },
    {
        "name": "BOILEROOM",
        "collectibles": {
            "anti_cubes": 1,
            "other": "Labyrinth Map 2"
        },
        "entrances": [
            {
                "volume_id": 1,
                "viewpoint":"RIGHT",
                "original_destination": "VILLAGEVILLE_3D"
            }
        ]
    },
    {
        "name": "GEEZER_HOUSE",
        "collectibles": {},
        "entrances": [
            {
                "volume_id": 1,
                "viewpoint": "RIGHT",
                "original_destination": "VILLAGEVILLE_3D"
            }
        ]
    },
    {
        "name": "SCHOOL",
        "collectibles": {
            "bits": 1
        },
        "entrances": [
            {
                "volume_id": 1,
                "viewpoint": "LEFT",
                "original_destination": "VILLAGEVILLE_3D"
            }
        ]
    },
    {
        "name": "KITCHEN",
        "collectibles": {
            "bits": 1
        },
        "entrances": [
            {
                "volume_id": 1,
                "viewpoint": "RIGHT",
                "original_destination": "VILLAGEVILLE_3D"
            }
        ]
    },
    {
        "name": "ABANDONED_A",
        "collectibles": {
            "bits": 1
        },
        "entrances": [
            {
                "volume_id": 1,
                "viewpoint": "RIGHT",
                "original_destination": "VILLAGEVILLE_3D"
            }
        ]
    },
    {
        "name": "ABANDONED_B",
        "collectibles": {
            "bits": 1
        },
        "entrances": [
            {
                "volume_id": 1,
                "viewpoint": "LEFT",
                "original_destination": "VILLAGEVILLE_3D"
            }
        ]
    },
    {
        "name": "ABANDONED_C",
        "collectibles": {},
        "entrances": [
            {
                "volume_id": 1,
                "viewpoint": "LEFT",
                "original_destination": "VILLAGEVILLE_3D"
            }
        ]
    },
    {
        "name": "BIG_TOWER",
        "collectibles": {
            "bits": 8
        },
        "entrances": [
            {
                "volume_id": 1,
                "viewpoint": "RIGHT",
                "original_destination": "VILLAGEVILLE_3D"
            },
            {
                "volume_id": 3,
                "viewpoint": "FRONT",
                "original_destination": "MEMORY_CORE",
                "cubes_required": 2
            }
        ]
    },
    {
        "name": "MEMORY_CORE",
        "collectibles": {},
        "entrances": [
            {
                "volume_id": 0,
                "viewpoint": "FRONT",
                "original_destination": "BIG_TOWER"
            },
            {
                "volume_id": 1,
                "viewpoint": "FRONT",
                "original_destination": "NATURE_HUB"
            },
            {
                "volume_id": 2,
                "viewpoint": "RIGHT",
                "original_destination": "WALL_VILLAGE",
                "cubes_required": 4
            },
            {
                "volume_id": 3,
                "viewpoint": "LEFT",
                "original_destination": "ZU_CITY",
                "cubes_required": 16
            },
            {
                "volume_id": 4,
                "viewpoint": "BACK",
                "original_destination": "INDUSTRIAL_CITY",
                "cubes_required": 8
            }
        ]
    },
    {
        "name": "WALL_VILLAGE",
        "collectibles": {
            "bits": 1
        },
        "entrances": [
            {
                "volume_id": 1,
                "viewpoint": "FRONT",
                "original_destination": "WALL_INTERIOR_A"
            },
            {
                "volume_id": 2,
                "viewpoint": "FRONT",
                "original_destination": "WALL_INTERIOR_B"
            },
            {
                "volume_id": 3,
                "viewpoint": "LEFT",
                "original_destination": "MEMORY_CORE"
            },
            {
                "volume_id": 4,
                "viewpoint": "FRONT",
                "original_destination": "WALL_INTERIOR_HOLE"
            },
            {
                "volume_id": 5,
                "viewpoint": "FRONT",
                "original_destination": "WALL_KITCHEN"
            },
            {
                "volume_id": 6,
                "viewpoint": "FRONT",
                "original_destination": "WALL_SCHOOL"
            }
        ]
    },
    {
        "name": "WALL_INTERIOR_A",
        "collectibles": {
            "bits": 1
        },
        "entrances": [
            {
                "volume_id": 0,
                "viewpoint": "LEFT",
                "original_destination": "WALL_VILLAGE"
            }
        ]
    },
    {
        "name": "WALL_INTERIOR_B",
        "collectibles": {},
        "entrances": [
            {
                "volume_id": 0,
                "viewpoint": "LEFT",
                "original_destination": "WALL_VILLAGE"
            }
        ]
    },
    {
        "name": "WALL_INTERIOR_HOLE",
        "collectibles": {},
        "entrances": [
            {
                "volume_id": 0,
                "viewpoint": "LEFT",
                "original_destination": "WALL_VILLAGE"
            }
        ]
    },
    {
        "name": "WALL_KITCHEN",
        "collectibles": {
            "bits": 1
        },
        "entrances": [
            {
                "volume_id": 0,
                "viewpoint": "LEFT",
                "original_destination": "WALL_VILLAGE"
            }
        ]
    },
    {
        "name": "WALL_SCHOOL",
        "collectibles": {
            "bits": 1
        },
        "entrances": [
            {
                "volume_id": 0,
                "viewpoint": "LEFT",
                "original_destination": "WALL_VILLAGE"
            }
        ]
    },
    {
        "name": "INDUSTRIAL_CITY",
        "collectibles": {},
        "entrances": [
            {
                "volume_id": 1,
                "viewpoint": "LEFT",
                "original_destination": "MEMORY_CORE"
            },
            {
                "volume_id": 2,
                "viewpoint": "BACK",
                "original_destination": "NUZU_SCHOOL"
            },
            {
                "volume_id": 3,
                "viewpoint": "LEFT",
                "original_destination": "NUZU_BOILERROOM"
            },
            {
                "volume_id": 4,
                "viewpoint": "FRONT",
                "original_destination": "NUZU_ABANDONED_A"
            },
            {
                "volume_id": 5,
                "viewpoint": "RIGHT",
                "original_destination": "SHOWERS"
            },
            {
                "volume_id": 6,
                "viewpoint": "RIGHT",
                "original_destination": "NUZU_DORM"
            }
        ]
    },
    {
        "name": "NUZU_SCHOOL",
        "collectibles": {
            "anti_cubes": 1
        },
        "entrances": [
            {
                "volume_id": 1,
                "viewpoint": "RIGHT",
                "original_destination": "INDUSTRIAL_CITY"
            }
        ]
    },
    {
        "name": "NUZU_BOILERROOM",
        "collectibles": {},
        "entrances": [
            {
                "volume_id": 1,
                "viewpoint": "LEFT",
                "original_destination": "INDUSTRIAL_CITY"
            }
        ]
    },
    {
        "name": "NUZU_ABANDONED_A",
        "collectibles": {
            "bits": 1
        },
        "entrances": [
            {
                "volume_id": 1,
                "viewpoint": "BACK",
                "original_destination": "INDUSTRIAL_CITY"
            }
        ]
    },
    {
        "name": "SHOWERS",
        "collectibles": {
            "bits": 1
        },
        "entrances": [
            {
                "volume_id": 1,
                "viewpoint": "LEFT",
                "original_destination": "INDUSTRIAL_CITY"
            }
        ]
    },
    {
        "name": "NUZU_DORM",
        "collectibles": {},
        "entrances": [
            {
                "volume_id": 1,
                "viewpoint": "RIGHT",
                "original_destination": "INDUSTRIAL_CITY"
            }
        ]
    },
    {
        "name": "ZU_CITY",
        "collectibles": {
            "bits": 2
        },
        "entrances": [
            {
                "volume_id": 2,
                "viewpoint": "LEFT",
                "original_destination": "MEMORY_CORE"
            },
            {
                "volume_id": 3,
                "viewpoint": "FRONT",
                "original_destination": "OLDSCHOOL"
            },
            {
                "volume_id": 4,
                "viewpoint": "RIGHT",
                "original_destination": "PURPLE_LODGE"
            },
            {
                "volume_id": 5,
                "viewpoint": "LEFT",
                "original_destination": "ZU_HOUSE_SCAFFOLDING"
            },
            {
                "volume_id": 6,
                "viewpoint": "BACK",
                "original_destination": "ZU_HOUSE_EMPTY"
            },
            {
                "volume_id": 7,
                "viewpoint": "LEFT",
                "original_destination": "ZU_HOUSE_EMPTY_B"
            }
        ]
    },
    {
        "name": "OLDSCHOOL",
        "collectibles": {
            "bits": 1
        },
        "entrances": [
            {
                "volume_id": 1,
                "viewpoint": "BACK",
                "original_destination": "ZU_CITY"
            }
        ]
    },
    {
        "name": "PURPLE_LODGE",
        "collectibles": {},
        "entrances": [
            {
                "volume_id": 2,
                "viewpoint": "FRONT",
                "original_destination": "ZU_CITY"
            }
        ]
    },
    {
        "name": "ZU_HOUSE_SCAFFOLDING",
        "collectibles": {
            "bits": 1
        },
        "entrances": [
            {
                "volume_id": 1,
                "viewpoint": "RIGHT",
                "original_destination": "ZU_CITY"
            }
        ]
    },
    {
        "name": "ZU_HOUSE_EMPTY",
        "collectibles": {
            "bits": 1,
            "anti_cubes": 1
        },
        "entrances": [
            {
                "volume_id": 1,
                "viewpoint": "LEFT",
                "original_destination": "ZU_CITY"
            }
        ]
    },
    {
        "name": "ZU_HOUSE_EMPTY_B",
        "collectibles": {},
        "entrances": [
            {
                "volume_id": 1,
                "viewpoint": "LEFT",
                "original_destination": "ZU_CITY"
            }
        ]
    },
    {
        "name": "NATURE_HUB",
        "collectibles": {
            "bits": 2
        },
        "entrances": [
            {
                "volume_id": 0,
                "viewpoint": "FRONT",
                "original_destination": "LIGHTHOUSE"
            },
            {
                "volume_id": 1,
                "viewpoint": "RIGHT",
                "original_destination": "ARCH"
            },
            {
                "volume_id": 2,
                "viewpoint": "BACK",
                "original_destination": "WATERFALL"
            },
            {
                "volume_id": 3,
                "viewpoint": "LEFT",
                "original_destination": "BELL_TOWER"
            },
            {
                "volume_id": 6,
                "viewpoint": "BACK",
                "original_destination": "MEMORY_CORE"
            },
            {
                "volume_id": 7,
                "viewpoint": "BACK",
                "original_destination": "TREE_ROOTS"
            },
            {
                "volume_id": 16,
                "viewpoint": "RIGHT",
                "original_destination": "RITUAL"
            }
        ]
    },
    {
        "name": "LIGHTHOUSE",
        "collectibles": {
            "other": "TODO"
        },
        "entrances": [
            {
                "volume_id": 7,
                "viewpoint": "FRONT",
                "original_destination": "NATURE_HUB"
            }
        ]
    },
    {
        "name": "ARCH",
        "collectibles": {
            "other": "TODO"
        },
        "entrances": [
            {
                "volume_id": 1,
                "viewpoint": "BACK",
                "original_destination": "NATURE_HUB"
            }
        ]
    },
    {
        "name": "WATERFALL",
        "collectibles": {
            "bits": 1,
            "owls": 1
        },
        "entrances": [
            {
                "volume_id": 0,
                "viewpoint": "LEFT",
                "original_destination": "FOX"
            },
            {
                "volume_id": 1,
                "viewpoint": "LEFT",
                "original_destination": "CMY"
            },
            {
                "volume_id": 3,
                "viewpoint": "BACK",
                "original_destination": "NATURE_HUB"
            },
            {
                "volume_id": 7,
                "viewpoint": "BACK",
                "original_destination": "WATER_WHEEL"
            },
            {
                "volume_id": 8,
                "viewpoint": "FRONT",
                "original_destination": "MINE_A"
            },
            {
                "volume_id": 9,
                "viewpoint": "RIGHT",
                "original_destination": "ZU_CODE_LOOP"
            },
            {
                "volume_id": 22,
                "viewpoint": "RIGHT",
                "original_destination": "ZU_ZUISH",
                "is_underwater": true
            }
        ]
    },
    {
        "name": "FOX",
        "collectibles" : {
            "bits": 1,
            "other": "writing_artifact"
        },
        "entrances": [
            {
                "volume_id": 1,
                "viewpoint": "FRONT",
                "original_destination": "WATERFALL"
            }
        ]
    },
    {
        "name": "CMY",
        "collectibles": {},
        "entrances": [
            {
                "volume_id": 2,
                "viewpoint": "BACK",
                "original_destination": "WATERFALL"
            },
            {
                "volume_id": 3,
                "viewpoint": "FRONT",
                "original_destination": "CMY_B"
            },
            {
                "volume_id": 4,
                "viewpoint": "LEFT",
                "original_destination": "CMY_FORK"
            }
        ]
    },
    {
        "name": "CMY_B",
        "collectibles": {
            "anti_cubes": 1
        },
        "entrances": [
            {
                "volume_id": 0,
                "viewpoint": "LEFT",
                "original_destination": "CMY"
            }
        ]
    },
    {
        "name": "CMY_FORK",
        "collectibles": {
            "anti_cubes": 1
        },
        "entrances": [
            {
                "volume_id": 4,
                "viewpoint": "FRONT",
                "original_destination": "CMY"
            }
        ]
    },
    {
        "name": "WATER_WHEEL",
        "collectibles": {},
        "entrances": [
            {
                "volume_id": 1,
                "viewpoint": "RIGHT",
                "original_destination": "WATERFALL"
            },
            {
                "volume_id": 2,
                "viewpoint": "FRONT",
                "original_destination": "WATER_WHEEL_B"
            }
        ]
    },
    {
        "name": "WATER_WHEEL_B",
        "collectibles": {
            "other": "Burnt Map"
        },
        "entrances": [
            {
                "volume_id": 1,
                "viewpoint": "RIGHT",
                "original_destination": "WATER_WHEEL"
            }
        ]
    },
    {
        "name": "MINE_A",
        "collectibles": {
            "bits": 1
        },
        "entrances": [
            {
                "volume_id": 0,
                "viewpoint": "RIGHT",
                "original_destination": "WATERFALL"
            },
            {
                "volume_id": 3,
                "viewpoint": "FRONT",
                "original_destination": "MINE_WRAP"
            }
        ]
    },
    {
        "name": "MINE_WRAP",
        "collectibles": {
            "golden_cubes": 1,
            "bits": 2
        },
        "entrances": [
            {
                "volume_id": 0,
                "viewpoint": "FRONT",
                "original_destination": "MINE_A"
            },
            {
                "volume_id": 1,
                "viewpoint": "LEFT",
                "original_destination": "MINE_BOMB_PILLAR"
            } 
        ]
    },
    {
        "name": "MINE_BOMB_PILLAR",
        "collectibles": {
            "bits": 1,
            "keys": 1
        },
        "entrances": [
            {
                "volume_id": 0,
                "viewpoint": "FRONT",
                "original_destination": "MINE_WRAP"
            }
        ]
    },
    {
        "name": "ZU_CODE_LOOP",
        "collectibles": {
            "anti_cubes": 1,
            "golden_cubes": 1,
            "bits": 2
        },
        "entrances": [
            {
                "volume_id": 0,
                "viewpoint": "BACK",
                "original_destination": "WATERFALL"
            }
        ]
    },
    {
        "name": "ZU_ZUISH",
        "collectibles": {
            "heart_pieces": 1
        },
        "entrances": [
            {
                "volume_id": 0,
                "viewpoint": "FRONT",
                "original_destination": "WATERFALL"
            }
        ]
    },
    {
        "name": "BELL_TOWER",
        "collectibles": {
            "other": "TODO"
        },
        "entrances": [
            {
                "volume_id": 1,
                "viewpoint": "BACK",
                "original_destination": "NATURE_HUB"
            }
        ]
    },
    {
        "name": "RITUAL",
        "collectibles": {
            "heart_pieces": 1
        },
        "entrances": [
            {
                "volume_id": 0,
                "viewpoint": "FRONT",
                "original_destination": "NATURE_HUB",
                "is_underwater": true
            }
        ]
    },
    {
        "name": "TREE_ROOTS",
        "collectibles": {},
        "entrances": [
            {
                "volume_id": 0,
                "viewpoint": "LEFT",
                "original_destination": "NATURE_HUB"
            }
        ]
    }
]